sod.py
sod-0.0.3.dist-info/LICENSE.txt
sod-0.0.3.dist-info/METADATA
sod-0.0.3.dist-info/WHEEL
sod-0.0.3.dist-info/top_level.txt
sod-0.0.3.dist-info/RECORD
