Metadata-Version: 2.1
Name: sod
Version: 0.0.3
Summary: Load and write .sod files.
Home-page: https://github.com/GoodClover/sod
Author: Oliver Simmons
Author-email: oliversimmo@gmail.com
License: UNKNOWN
Platform: UNKNOWN
Classifier: Programming Language :: Python :: 3
Classifier: Programming Language :: Python :: 3.9
Classifier: Programming Language :: Python :: 3.8
Classifier: Programming Language :: Python :: 3.7
Classifier: License :: OSI Approved :: MIT License
Classifier: Operating System :: OS Independent
Requires-Python: >=3.7
